{
	"returnCode": "0",
	"returnMsg": "ok",
	"pgUpDownFlag": "next",
	"totalNum": 1,
	"pagePerNum": 25,
	"currentNum": 1,
	"totalPage":1,
	"result": [{
			"productId": "2342342-45664-2223",
			"productCode": "010232",
			"productName": "lenova T460",
			"productTypeId": "432545-545435-45345435-54435",
			"brandId": " 432545-545435-23423423-52435",
			"productLineId": " 432545-34354-23423423-52435",
			"productCategroy": "single",
			"productDivision": "01",
			"upcCode": null,
			"description": "lenovo desktop computer",
			"defaultWarehouseId": "423423423-234234-23423",
			"abcLevel": "A",
			"stockQty": 1250,
			"stockAmount": 1250000,
			"isUIDMgr": "N",
			"isBatchMgr": "N",
			"isShelfLifeMgr": "N",
			"isSKUMgr": "Y",
			"status": "Y",
			"productUnit": "台",
			"activeStartTime": "2018-10-18 17:40:50.3244",
			"activeEndTime": "2118-10-18 17:40:50.3244",
			"createdTime": "2018-11-10  09:30:00",
			"creatorId": "1001",
			"creatorName": "张三",
			"modifyTime": "2018-11-20 09: 43: 20 ",
			"modifierId": "1001",
			"modifierName": "张三",
			"lastModifyTime": "2018-11-20  09:43:20:123",
			"ownerCompanyCode": "20382302",
			"tenantId": "qloudfin"
		},
		{
			"productId": "2342342-45664-2113",
			"productCode": "0102334",
			"productName": "苹果iphone6",
			"productTypeId": "432545-545435-45345435-1248",
			"brandId": " 432545-545435-23423423-123",
			"productLineId": " 432545-34354-23423423-12",
			"productCategroy": "single",
			"productDivision": "01",
			"upcCode": null,
			"description": "苹果6",
			"defaultWarehouseId": "423423423-234234-23423",
			"abcLevel": "A",
			"stockQty": 1250,
			"stockAmount": 1250000,
			"isUIDMgr": "N",
			"isBatchMgr": "N",
			"isShelfLifeMgr": "N",
			"isSKUMgr": "Y",
			"status": "Y",
			"productUnit": "台",
			"activeStartTime": "2018-10-18 17:40:50.3244",
			"activeEndTime": "2118-12-18 17:40:50.3244",
			"createdTime": "2018-11-10  09:30:00",
			"creatorId": "1001",
			"creatorName": "张三",
			"modifyTime": "2018-11-20 09: 43: 20",
			"modifierId": "1001",
			"modifierName": "张三",
			"lastModifyTime": "2018-11-20  09:43:20:123",
			"ownerCompanyCode": "20382302",
			"tenantId": "qloudfin"
		}
	]
}