{
	"returnCode":"0", 
	"returnMsg":"ok",
	"pgUpDownFlag":"next",
	"totalNum":20,
	"pagePerNum":25, 
	"currentNum":1,
	"result": 
	[
	{
		"groupId": "2000-1",
		"groupName": "手机详情",
		"sort": "1",
		"status": "Y", 
		"productTypeId": "3213244-43423545-54254545",
		"createdTime": "2018-11-10  09:30:00",
		"creatorId": "1001",
		"creatorName": "张三",
		"modifyTime": "2018-11-20  09:43:20" ,
		"modifierId": "1001",
		"modifierName": "张三",
		"lastModifyTime": "2018-11-20  09:43:20:123",
		"tenantId": "qloudfin"
	}
	]
}
